doing/__init__.py
doing/cli.py
doing/exceptions.py
doing/options.py
doing/utils.py
doing/init/__init__.py
doing/init/_init.py
doing/init/commands.py
doing/issue/__init__.py
doing/issue/commands.py
doing/issue/create_issue.py
doing/issue/open_issue.py
doing/list/__init__.py
doing/list/_list.py
doing/list/commands.py
doing/open/__init__.py
doing/open/commands.py
doing/pr/__init__.py
doing/pr/commands.py
doing/pr/create_pr.py
doing/pr/list_pr.py
doing/pr/open_pr.py
doing/workon/__init__.py
doing/workon/commands.py
doing_cli-1.5.3.dist-info/LICENSE
doing_cli-1.5.3.dist-info/METADATA
doing_cli-1.5.3.dist-info/WHEEL
doing_cli-1.5.3.dist-info/entry_points.txt
doing_cli-1.5.3.dist-info/top_level.txt
doing_cli-1.5.3.dist-info/RECORD
