Metadata-Version: 2.1
Name: doing-cli
Version: 1.5.3
Summary: CLI tool to simplify the development workflow on azure devops
Home-page: https://github.com/ing-bank/doing-cli
Author: ING Bank N.V.
Author-email: tim.vink@ing.com
License: MIT
Classifier: Intended Audience :: Developers
Classifier: Programming Language :: Python :: 3
Classifier: Programming Language :: Python :: 3.8
Classifier: Programming Language :: Python :: 3.9
Classifier: Programming Language :: Python :: 3.10
Classifier: Programming Language :: Python :: 3.11
Classifier: License :: OSI Approved :: MIT License
Classifier: Operating System :: OS Independent
Requires-Python: >=3.7
License-File: LICENSE
Requires-Dist: Click (>=8.0.1)
Requires-Dist: rich (>=10.3.0)
Requires-Dist: pyyaml (>=5.4.1)
Requires-Dist: timeago (>=1.0.15)
Requires-Dist: psutil (>=5.8.0)
Provides-Extra: all
Requires-Dist: Click (>=8.0.1) ; extra == 'all'
Requires-Dist: rich (>=10.3.0) ; extra == 'all'
Requires-Dist: pyyaml (>=5.4.1) ; extra == 'all'
Requires-Dist: timeago (>=1.0.15) ; extra == 'all'
Requires-Dist: psutil (>=5.8.0) ; extra == 'all'
Requires-Dist: mkdocs-material (>=7.1) ; extra == 'all'
Requires-Dist: mkdocs-macros-plugin ; extra == 'all'
Requires-Dist: pytest ; extra == 'all'
Requires-Dist: pytest-cov ; extra == 'all'
Requires-Dist: pytest-mock ; extra == 'all'
Requires-Dist: pre-commit ; extra == 'all'
Requires-Dist: black ; extra == 'all'
Requires-Dist: flake8 ; extra == 'all'
Requires-Dist: mypy ; extra == 'all'
Requires-Dist: isort ; extra == 'all'
